[{"config":"Chromium 1920","suite":"searxng.spec.js","test_case":"preferences","attachments":[{"uid":"3798847fe1143a35","name":"preferences-General","source":"3798847fe1143a35.png","type":"image/png","size":117995},{"uid":"fb6a5d5d934740da","name":"preferences-User interface","source":"fb6a5d5d934740da.png","type":"image/png","size":120366},{"uid":"2c50591c912efc85","name":"preferences-Privacy","source":"2c50591c912efc85.png","type":"image/png","size":92629},{"uid":"3fc27aa44c1946af","name":"preferences-Engines","source":"3fc27aa44c1946af.png","type":"image/png","size":93882},{"uid":"855772fdbab961c9","name":"preferences-Special Queries","source":"855772fdbab961c9.png","type":"image/png","size":134220},{"uid":"d0fab1b4f251fc69","name":"preferences-Cookies","source":"d0fab1b4f251fc69.png","type":"image/png","size":129714},{"uid":"891200ac9a14c85b","name":"preferences_console","source":"891200ac9a14c85b.json","type":"application/json","size":2,"content":[]}]},{"config":"Chromium 1920","suite":"searxng.spec.js","test_case":"index","attachments":[{"uid":"bfa7fda76130f5ea","name":"index","source":"bfa7fda76130f5ea.png","type":"image/png","size":45485},{"uid":"eb37f82c2ff6a23","name":"index_autocomplete","source":"eb37f82c2ff6a23.png","type":"image/png","size":44656},{"uid":"1e9898ae171d8bda","name":"index_console","source":"1e9898ae171d8bda.json","type":"application/json","size":2,"content":[]}]},{"config":"Chromium 1920","suite":"searxng.spec.js","test_case":"search_general","attachments":[{"uid":"30408dc8c4c70f55","name":"search_general","source":"30408dc8c4c70f55.png","type":"image/png","size":412697},{"uid":"7f427bc33ce40d11","name":"search_general_2","source":"7f427bc33ce40d11.png","type":"image/png","size":198242},{"uid":"59558f899baa75db","name":"search_general_console","source":"59558f899baa75db.json","type":"application/json","size":2,"content":[]}]},{"config":"Chromium 1920","suite":"searxng.spec.js","test_case":"search_images","attachments":[{"uid":"719aabf6ce0a322f","name":"search_images","source":"719aabf6ce0a322f.png","type":"image/png","size":1993626},{"uid":"c97183fc4bd2b691","name":"search_images_detail","source":"c97183fc4bd2b691.png","type":"image/png","size":1321281},{"uid":"ba51d02d5c6ef8c9","name":"search_images_console","source":"ba51d02d5c6ef8c9.json","type":"application/json","size":2,"content":[]}]},{"config":"Chromium 1920","suite":"searxng.spec.js","test_case":"search_videos","attachments":[{"uid":"52d6e2b65066e2f","name":"search_videos","source":"52d6e2b65066e2f.png","type":"image/png","size":305308},{"uid":"bc1040aae38731b0","name":"search_videos_player","source":"bc1040aae38731b0.png","type":"image/png","size":291577},{"uid":"a8d10d808733ae99","name":"search_videos_console","source":"a8d10d808733ae99.json","type":"application/json","size":2,"content":[]}]},{"config":"Chromium 1920","suite":"searxng.spec.js","test_case":"search_map","attachments":[{"uid":"ccd75f8f7507c1e","name":"search_map","source":"ccd75f8f7507c1e.png","type":"image/png","size":175994},{"uid":"b5a3f5201c08ed72","name":"search_map_detail","source":"b5a3f5201c08ed72.png","type":"image/png","size":476314},{"uid":"966046b8439af3fe","name":"search_map_console","source":"966046b8439af3fe.json","type":"application/json","size":2,"content":[]}]},{"config":"Chromium 1920","suite":"searxng.spec.js","test_case":"search_code","attachments":[{"uid":"6aff0381b8baafbb","name":"search_code","source":"6aff0381b8baafbb.png","type":"image/png","size":71425},{"uid":"970b3cfc0cd8da69","name":"search_code_console","source":"970b3cfc0cd8da69.json","type":"application/json","size":2,"content":[]}]},{"config":"Chromium 1920","suite":"searxng.spec.js","test_case":"about","attachments":[{"uid":"a664ddd279942e04","name":"about","source":"a664ddd279942e04.png","type":"image/png","size":228493},{"uid":"1083af6600f98cd9","name":"about_console","source":"1083af6600f98cd9.json","type":"application/json","size":2,"content":[]}]},{"config":"Firefox 1920","suite":"searxng.spec.js","test_case":"preferences","attachments":[{"uid":"7ae0c7c9e311aeeb","name":"preferences-General","source":"7ae0c7c9e311aeeb.png","type":"image/png","size":136768},{"uid":"af08e4afabefc4b1","name":"preferences-User interface","source":"af08e4afabefc4b1.png","type":"image/png","size":141400},{"uid":"fdd17f4a5164efb4","name":"preferences-Privacy","source":"fdd17f4a5164efb4.png","type":"image/png","size":115163},{"uid":"cd9a25b229b91cc","name":"preferences-Engines","source":"cd9a25b229b91cc.png","type":"image/png","size":124464},{"uid":"84430126501d47d","name":"preferences-Special Queries","source":"84430126501d47d.png","type":"image/png","size":153110},{"uid":"21dc73e335a602c7","name":"preferences-Cookies","source":"21dc73e335a602c7.png","type":"image/png","size":146703},{"uid":"574d39419fae3119","name":"preferences_console","source":"574d39419fae3119.json","type":"application/json","size":2,"content":[]}]},{"config":"Firefox 1920","suite":"searxng.spec.js","test_case":"index","attachments":[{"uid":"965fdd1a4a529482","name":"index","source":"965fdd1a4a529482.png","type":"image/png","size":85461},{"uid":"7e282f01a8ead2fe","name":"index_autocomplete","source":"7e282f01a8ead2fe.png","type":"image/png","size":84744},{"uid":"ecb57e56f875b763","name":"index_console","source":"ecb57e56f875b763.json","type":"application/json","size":2,"content":[]}]},{"config":"Firefox 1920","suite":"searxng.spec.js","test_case":"search_general","attachments":[{"uid":"d9d6139d1adeac27","name":"search_general","source":"d9d6139d1adeac27.png","type":"image/png","size":429280},{"uid":"7b881caeff5c0791","name":"search_general_2","source":"7b881caeff5c0791.png","type":"image/png","size":211070},{"uid":"50ce5c5464a823a2","name":"search_general_console","source":"50ce5c5464a823a2.json","type":"application/json","size":2,"content":[]}]},{"config":"Firefox 1920","suite":"searxng.spec.js","test_case":"search_images","attachments":[{"uid":"55ca452598fb8c84","name":"search_images","source":"55ca452598fb8c84.png","type":"image/png","size":2300403},{"uid":"d4b3a202142980a0","name":"search_images_detail","source":"d4b3a202142980a0.png","type":"image/png","size":1694931},{"uid":"de9e541b382a23d8","name":"search_images_console","source":"de9e541b382a23d8.json","type":"application/json","size":2,"content":[]}]},{"config":"Firefox 1920","suite":"searxng.spec.js","test_case":"search_videos","attachments":[{"uid":"fbce83d374d576f7","name":"search_videos","source":"fbce83d374d576f7.png","type":"image/png","size":360694},{"uid":"16103fa598f01988","name":"search_videos_player","source":"16103fa598f01988.png","type":"image/png","size":347282},{"uid":"88a86911afee41c","name":"search_videos_console","source":"88a86911afee41c.json","type":"application/json","size":1840,"content":[{"type":"warn","text":"[JavaScript Warning: \"Cookie “LAST_RESULT_ENTRY_KEY” will be soon rejected because it has the “SameSite” attribute set to “None” or an invalid value, without the “secure” attribute. To know more about the “SameSite“ attribute, read https://developer.mozilla.org/docs/Web/HTTP/Headers/Set-Cookie/SameSite\" {file: \"https://www.youtube-nocookie.com/s/player/c8b8a173/www-embed-player.vflset/www-embed-player.js\" line: 462}]"},{"type":"warn","text":"[JavaScript Warning: \"Cookie “nextId” will be soon rejected because it has the “SameSite” attribute set to “None” or an invalid value, without the “secure” attribute. To know more about the “SameSite“ attribute, read https://developer.mozilla.org/docs/Web/HTTP/Headers/Set-Cookie/SameSite\" {file: \"https://www.youtube-nocookie.com/s/player/c8b8a173/www-embed-player.vflset/www-embed-player.js\" line: 462}]"},{"type":"warn","text":"[JavaScript Warning: \"Cookie “requests” will be soon rejected because it has the “SameSite” attribute set to “None” or an invalid value, without the “secure” attribute. To know more about the “SameSite“ attribute, read https://developer.mozilla.org/docs/Web/HTTP/Headers/Set-Cookie/SameSite\" {file: \"https://www.youtube-nocookie.com/s/player/c8b8a173/www-embed-player.vflset/www-embed-player.js\" line: 462}]"},{"type":"warn","text":"[JavaScript Warning: \"Cookie “requests” will be soon rejected because it has the “SameSite” attribute set to “None” or an invalid value, without the “secure” attribute. To know more about the “SameSite“ attribute, read https://developer.mozilla.org/docs/Web/HTTP/Headers/Set-Cookie/SameSite\" {file: \"https://www.youtube-nocookie.com/s/player/c8b8a173/www-embed-player.vflset/www-embed-player.js\" line: 462}]"}]}]},{"config":"Firefox 1920","suite":"searxng.spec.js","test_case":"search_map","attachments":[{"uid":"4416b2e5637eafb1","name":"search_map","source":"4416b2e5637eafb1.png","type":"image/png","size":216522},{"uid":"bd24ce5416f7704d","name":"search_map_detail","source":"bd24ce5416f7704d.png","type":"image/png","size":516630},{"uid":"83e0a47d2a44898a","name":"search_map_console","source":"83e0a47d2a44898a.json","type":"application/json","size":2,"content":[]}]},{"config":"Firefox 1920","suite":"searxng.spec.js","test_case":"search_code","attachments":[{"uid":"590699c6b759b847","name":"search_code","source":"590699c6b759b847.png","type":"image/png","size":253758},{"uid":"857e99d2fc05f710","name":"search_code_console","source":"857e99d2fc05f710.json","type":"application/json","size":2,"content":[]}]},{"config":"Firefox 1920","suite":"searxng.spec.js","test_case":"about","attachments":[{"uid":"6f301bd7111da184","name":"about","source":"6f301bd7111da184.png","type":"image/png","size":241103},{"uid":"3de75024cd89e9b3","name":"about_console","source":"3de75024cd89e9b3.json","type":"application/json","size":2,"content":[]}]},{"config":"Firefox 1280","suite":"searxng.spec.js","test_case":"preferences","attachments":[{"uid":"857daee604725446","name":"preferences-General","source":"857daee604725446.png","type":"image/png","size":117483},{"uid":"e70c9143a0086cac","name":"preferences-User interface","source":"e70c9143a0086cac.png","type":"image/png","size":121688},{"uid":"ed3764c11544c096","name":"preferences-Privacy","source":"ed3764c11544c096.png","type":"image/png","size":97353},{"uid":"e5cf2dd20c1bf860","name":"preferences-Engines","source":"e5cf2dd20c1bf860.png","type":"image/png","size":97272},{"uid":"23c535224a667fd0","name":"preferences-Special Queries","source":"23c535224a667fd0.png","type":"image/png","size":132601},{"uid":"51bef0b20c03e323","name":"preferences-Cookies","source":"51bef0b20c03e323.png","type":"image/png","size":127154},{"uid":"a57d302e44e7a727","name":"preferences_console","source":"a57d302e44e7a727.json","type":"application/json","size":2,"content":[]}]},{"config":"Firefox 1280","suite":"searxng.spec.js","test_case":"index","attachments":[{"uid":"a44e4ccc6d2f666e","name":"index","source":"a44e4ccc6d2f666e.png","type":"image/png","size":70018},{"uid":"26cb5f1dfb4403a4","name":"index_autocomplete","source":"26cb5f1dfb4403a4.png","type":"image/png","size":69033},{"uid":"d9ec27c62ac715f7","name":"index_console","source":"d9ec27c62ac715f7.json","type":"application/json","size":2,"content":[]}]},{"config":"Firefox 1280","suite":"searxng.spec.js","test_case":"search_general","attachments":[{"uid":"20ed70dc7b273090","name":"search_general","source":"20ed70dc7b273090.png","type":"image/png","size":366350},{"uid":"9c92da56d47c9a6b","name":"search_general_2","source":"9c92da56d47c9a6b.png","type":"image/png","size":172772},{"uid":"39374c75c8cec480","name":"search_general_console","source":"39374c75c8cec480.json","type":"application/json","size":2,"content":[]}]},{"config":"Firefox 1280","suite":"searxng.spec.js","test_case":"search_images","attachments":[{"uid":"baf2c14ecaea144d","name":"search_images","source":"baf2c14ecaea144d.png","type":"image/png","size":1333189},{"uid":"6403c0520aaaab06","name":"search_images_detail","source":"6403c0520aaaab06.png","type":"image/png","size":998861},{"uid":"b8271bc06b17a005","name":"search_images_console","source":"b8271bc06b17a005.json","type":"application/json","size":2,"content":[]}]},{"config":"Firefox 1280","suite":"searxng.spec.js","test_case":"search_videos","attachments":[{"uid":"4b3f335b0eab72da","name":"search_videos","source":"4b3f335b0eab72da.png","type":"image/png","size":320617},{"uid":"b83a01f4be38abd7","name":"search_videos_player","source":"b83a01f4be38abd7.png","type":"image/png","size":274536},{"uid":"c62ca01de783e0fc","name":"search_videos_console","source":"c62ca01de783e0fc.json","type":"application/json","size":1840,"content":[{"type":"warn","text":"[JavaScript Warning: \"Cookie “LAST_RESULT_ENTRY_KEY” will be soon rejected because it has the “SameSite” attribute set to “None” or an invalid value, without the “secure” attribute. To know more about the “SameSite“ attribute, read https://developer.mozilla.org/docs/Web/HTTP/Headers/Set-Cookie/SameSite\" {file: \"https://www.youtube-nocookie.com/s/player/c8b8a173/www-embed-player.vflset/www-embed-player.js\" line: 462}]"},{"type":"warn","text":"[JavaScript Warning: \"Cookie “nextId” will be soon rejected because it has the “SameSite” attribute set to “None” or an invalid value, without the “secure” attribute. To know more about the “SameSite“ attribute, read https://developer.mozilla.org/docs/Web/HTTP/Headers/Set-Cookie/SameSite\" {file: \"https://www.youtube-nocookie.com/s/player/c8b8a173/www-embed-player.vflset/www-embed-player.js\" line: 462}]"},{"type":"warn","text":"[JavaScript Warning: \"Cookie “requests” will be soon rejected because it has the “SameSite” attribute set to “None” or an invalid value, without the “secure” attribute. To know more about the “SameSite“ attribute, read https://developer.mozilla.org/docs/Web/HTTP/Headers/Set-Cookie/SameSite\" {file: \"https://www.youtube-nocookie.com/s/player/c8b8a173/www-embed-player.vflset/www-embed-player.js\" line: 462}]"},{"type":"warn","text":"[JavaScript Warning: \"Cookie “requests” will be soon rejected because it has the “SameSite” attribute set to “None” or an invalid value, without the “secure” attribute. To know more about the “SameSite“ attribute, read https://developer.mozilla.org/docs/Web/HTTP/Headers/Set-Cookie/SameSite\" {file: \"https://www.youtube-nocookie.com/s/player/c8b8a173/www-embed-player.vflset/www-embed-player.js\" line: 462}]"}]}]},{"config":"Firefox 1280","suite":"searxng.spec.js","test_case":"search_map","attachments":[{"uid":"113a430f345f233b","name":"search_map","source":"113a430f345f233b.png","type":"image/png","size":183497},{"uid":"b00adf4efc2735fd","name":"search_map_detail","source":"b00adf4efc2735fd.png","type":"image/png","size":473197},{"uid":"d0d297a36f313e8","name":"search_map_console","source":"d0d297a36f313e8.json","type":"application/json","size":2,"content":[]}]},{"config":"Firefox 1280","suite":"searxng.spec.js","test_case":"search_code","attachments":[{"uid":"ba453fa94ef0bbd6","name":"search_code","source":"ba453fa94ef0bbd6.png","type":"image/png","size":208086},{"uid":"e5fac328bad13675","name":"search_code_console","source":"e5fac328bad13675.json","type":"application/json","size":2,"content":[]}]},{"config":"Firefox 1280","suite":"searxng.spec.js","test_case":"about","attachments":[{"uid":"a76c39f8d7239364","name":"about","source":"a76c39f8d7239364.png","type":"image/png","size":204541},{"uid":"e20c0abfb715f05","name":"about_console","source":"e20c0abfb715f05.json","type":"application/json","size":2,"content":[]}]},{"config":"Firefox 1024","suite":"searxng.spec.js","test_case":"preferences","attachments":[{"uid":"6bfdb3aad197f8dc","name":"preferences-General","source":"6bfdb3aad197f8dc.png","type":"image/png","size":84553},{"uid":"fc2fceb3f0b1b3a8","name":"preferences-User interface","source":"fc2fceb3f0b1b3a8.png","type":"image/png","size":83770},{"uid":"1bb5b6acce681388","name":"preferences-Privacy","source":"1bb5b6acce681388.png","type":"image/png","size":88928},{"uid":"258bbdefd4f72783","name":"preferences-Engines","source":"258bbdefd4f72783.png","type":"image/png","size":76703},{"uid":"3de0eefe79dde8dc","name":"preferences-Special Queries","source":"3de0eefe79dde8dc.png","type":"image/png","size":109810},{"uid":"46b643157330bcfd","name":"preferences-Cookies","source":"46b643157330bcfd.png","type":"image/png","size":111236},{"uid":"8ca30e55f6fda985","name":"preferences_console","source":"8ca30e55f6fda985.json","type":"application/json","size":2,"content":[]}]},{"config":"Firefox 1024","suite":"searxng.spec.js","test_case":"index","attachments":[{"uid":"dd304233eac93319","name":"index","source":"dd304233eac93319.png","type":"image/png","size":55771},{"uid":"eeccf1132d7f5c7","name":"index_autocomplete","source":"eeccf1132d7f5c7.png","type":"image/png","size":55002},{"uid":"76b603371febe5eb","name":"index_console","source":"76b603371febe5eb.json","type":"application/json","size":2,"content":[]}]},{"config":"Firefox 1024","suite":"searxng.spec.js","test_case":"search_general","attachments":[{"uid":"56fcda83191ccd9d","name":"search_general","source":"56fcda83191ccd9d.png","type":"image/png","size":196141},{"uid":"cafbba1f7b97dac4","name":"search_general_2","source":"cafbba1f7b97dac4.png","type":"image/png","size":128164},{"uid":"c7a71ec8ffa1b06a","name":"search_general_console","source":"c7a71ec8ffa1b06a.json","type":"application/json","size":2,"content":[]}]},{"config":"Firefox 1024","suite":"searxng.spec.js","test_case":"search_images","attachments":[{"uid":"5d9370770046adb0","name":"search_images","source":"5d9370770046adb0.png","type":"image/png","size":821462},{"uid":"b7dac2a18f70b89f","name":"search_images_detail","source":"b7dac2a18f70b89f.png","type":"image/png","size":433683},{"uid":"e08ba223e64f0440","name":"search_images_console","source":"e08ba223e64f0440.json","type":"application/json","size":2,"content":[]}]},{"config":"Firefox 1024","suite":"searxng.spec.js","test_case":"search_videos","attachments":[{"uid":"2fb7c686013a6864","name":"search_videos","source":"2fb7c686013a6864.png","type":"image/png","size":195753},{"uid":"5101bed6fba93a18","name":"search_videos_player","source":"5101bed6fba93a18.png","type":"image/png","size":188636},{"uid":"7925e996730842ba","name":"search_videos_console","source":"7925e996730842ba.json","type":"application/json","size":1840,"content":[{"type":"warn","text":"[JavaScript Warning: \"Cookie “LAST_RESULT_ENTRY_KEY” will be soon rejected because it has the “SameSite” attribute set to “None” or an invalid value, without the “secure” attribute. To know more about the “SameSite“ attribute, read https://developer.mozilla.org/docs/Web/HTTP/Headers/Set-Cookie/SameSite\" {file: \"https://www.youtube-nocookie.com/s/player/c8b8a173/www-embed-player.vflset/www-embed-player.js\" line: 462}]"},{"type":"warn","text":"[JavaScript Warning: \"Cookie “nextId” will be soon rejected because it has the “SameSite” attribute set to “None” or an invalid value, without the “secure” attribute. To know more about the “SameSite“ attribute, read https://developer.mozilla.org/docs/Web/HTTP/Headers/Set-Cookie/SameSite\" {file: \"https://www.youtube-nocookie.com/s/player/c8b8a173/www-embed-player.vflset/www-embed-player.js\" line: 462}]"},{"type":"warn","text":"[JavaScript Warning: \"Cookie “requests” will be soon rejected because it has the “SameSite” attribute set to “None” or an invalid value, without the “secure” attribute. To know more about the “SameSite“ attribute, read https://developer.mozilla.org/docs/Web/HTTP/Headers/Set-Cookie/SameSite\" {file: \"https://www.youtube-nocookie.com/s/player/c8b8a173/www-embed-player.vflset/www-embed-player.js\" line: 462}]"},{"type":"warn","text":"[JavaScript Warning: \"Cookie “requests” will be soon rejected because it has the “SameSite” attribute set to “None” or an invalid value, without the “secure” attribute. To know more about the “SameSite“ attribute, read https://developer.mozilla.org/docs/Web/HTTP/Headers/Set-Cookie/SameSite\" {file: \"https://www.youtube-nocookie.com/s/player/c8b8a173/www-embed-player.vflset/www-embed-player.js\" line: 462}]"}]}]},{"config":"Firefox 1024","suite":"searxng.spec.js","test_case":"search_map","attachments":[{"uid":"d37b66770a7e5f92","name":"search_map","source":"d37b66770a7e5f92.png","type":"image/png","size":142355},{"uid":"c0b959a63920c785","name":"search_map_detail","source":"c0b959a63920c785.png","type":"image/png","size":429517},{"uid":"2b003fb247e8edf6","name":"search_map_console","source":"2b003fb247e8edf6.json","type":"application/json","size":2,"content":[]}]},{"config":"Firefox 1024","suite":"searxng.spec.js","test_case":"search_code","attachments":[{"uid":"9acc96c2a4d4b5e4","name":"search_code","source":"9acc96c2a4d4b5e4.png","type":"image/png","size":155588},{"uid":"6fdf4b3b50538269","name":"search_code_console","source":"6fdf4b3b50538269.json","type":"application/json","size":2,"content":[]}]},{"config":"Firefox 1024","suite":"searxng.spec.js","test_case":"about","attachments":[{"uid":"20da381b5a9a6975","name":"about","source":"20da381b5a9a6975.png","type":"image/png","size":161346},{"uid":"f9d8e9c723c3b6ae","name":"about_console","source":"f9d8e9c723c3b6ae.json","type":"application/json","size":2,"content":[]}]},{"config":"Firefox 1024 - centered","suite":"searxng.spec.js","test_case":"preferences","attachments":[{"uid":"237e0751cbebc20b","name":"preferences-General","source":"237e0751cbebc20b.png","type":"image/png","size":84553},{"uid":"e4b1d55f8fe5c317","name":"preferences-User interface","source":"e4b1d55f8fe5c317.png","type":"image/png","size":83770},{"uid":"b023ea8d04f2dd28","name":"preferences-Privacy","source":"b023ea8d04f2dd28.png","type":"image/png","size":88928},{"uid":"aaf02d324f5e3dc5","name":"preferences-Engines","source":"aaf02d324f5e3dc5.png","type":"image/png","size":76678},{"uid":"7022888c0a0db232","name":"preferences-Special Queries","source":"7022888c0a0db232.png","type":"image/png","size":109810},{"uid":"d1658a70724ef04f","name":"preferences-Cookies","source":"d1658a70724ef04f.png","type":"image/png","size":101178},{"uid":"d662a0d9dbee6e06","name":"preferences_console","source":"d662a0d9dbee6e06.json","type":"application/json","size":2,"content":[]}]},{"config":"Firefox 1024 - centered","suite":"searxng.spec.js","test_case":"index","attachments":[{"uid":"817300916c07bb60","name":"index","source":"817300916c07bb60.png","type":"image/png","size":55771},{"uid":"ab079cfa762e0d17","name":"index_autocomplete","source":"ab079cfa762e0d17.png","type":"image/png","size":55002},{"uid":"fe11957a5605480b","name":"index_console","source":"fe11957a5605480b.json","type":"application/json","size":2,"content":[]}]},{"config":"Firefox 1024 - centered","suite":"searxng.spec.js","test_case":"search_general","attachments":[{"uid":"9de4d774386206b7","name":"search_general","source":"9de4d774386206b7.png","type":"image/png","size":197024},{"uid":"74341bf27444bc87","name":"search_general_2","source":"74341bf27444bc87.png","type":"image/png","size":128457},{"uid":"20ea214f6dc454c","name":"search_general_console","source":"20ea214f6dc454c.json","type":"application/json","size":2,"content":[]}]},{"config":"Firefox 1024 - centered","suite":"searxng.spec.js","test_case":"search_images","attachments":[{"uid":"3f850a962ed2b000","name":"search_images","source":"3f850a962ed2b000.png","type":"image/png","size":801076},{"uid":"51ef72b6c844120a","name":"search_images_detail","source":"51ef72b6c844120a.png","type":"image/png","size":433683},{"uid":"2bd2ccee6539cf88","name":"search_images_console","source":"2bd2ccee6539cf88.json","type":"application/json","size":2,"content":[]}]},{"config":"Firefox 1024 - centered","suite":"searxng.spec.js","test_case":"search_videos","attachments":[{"uid":"b3695ccd36f5ef17","name":"search_videos","source":"b3695ccd36f5ef17.png","type":"image/png","size":158548},{"uid":"d8089057b23ec84f","name":"search_videos_player","source":"d8089057b23ec84f.png","type":"image/png","size":186796},{"uid":"2aafed48e0d121bb","name":"search_videos_console","source":"2aafed48e0d121bb.json","type":"application/json","size":1840,"content":[{"type":"warn","text":"[JavaScript Warning: \"Cookie “LAST_RESULT_ENTRY_KEY” will be soon rejected because it has the “SameSite” attribute set to “None” or an invalid value, without the “secure” attribute. To know more about the “SameSite“ attribute, read https://developer.mozilla.org/docs/Web/HTTP/Headers/Set-Cookie/SameSite\" {file: \"https://www.youtube-nocookie.com/s/player/c8b8a173/www-embed-player.vflset/www-embed-player.js\" line: 462}]"},{"type":"warn","text":"[JavaScript Warning: \"Cookie “nextId” will be soon rejected because it has the “SameSite” attribute set to “None” or an invalid value, without the “secure” attribute. To know more about the “SameSite“ attribute, read https://developer.mozilla.org/docs/Web/HTTP/Headers/Set-Cookie/SameSite\" {file: \"https://www.youtube-nocookie.com/s/player/c8b8a173/www-embed-player.vflset/www-embed-player.js\" line: 462}]"},{"type":"warn","text":"[JavaScript Warning: \"Cookie “requests” will be soon rejected because it has the “SameSite” attribute set to “None” or an invalid value, without the “secure” attribute. To know more about the “SameSite“ attribute, read https://developer.mozilla.org/docs/Web/HTTP/Headers/Set-Cookie/SameSite\" {file: \"https://www.youtube-nocookie.com/s/player/c8b8a173/www-embed-player.vflset/www-embed-player.js\" line: 462}]"},{"type":"warn","text":"[JavaScript Warning: \"Cookie “requests” will be soon rejected because it has the “SameSite” attribute set to “None” or an invalid value, without the “secure” attribute. To know more about the “SameSite“ attribute, read https://developer.mozilla.org/docs/Web/HTTP/Headers/Set-Cookie/SameSite\" {file: \"https://www.youtube-nocookie.com/s/player/c8b8a173/www-embed-player.vflset/www-embed-player.js\" line: 462}]"}]}]},{"config":"Firefox 1024 - centered","suite":"searxng.spec.js","test_case":"search_map","attachments":[{"uid":"56f9da26fa331bc7","name":"search_map","source":"56f9da26fa331bc7.png","type":"image/png","size":142355},{"uid":"ee9de6d4db1ec118","name":"search_map_detail","source":"ee9de6d4db1ec118.png","type":"image/png","size":429517},{"uid":"2950e5a029709ea2","name":"search_map_console","source":"2950e5a029709ea2.json","type":"application/json","size":2,"content":[]}]},{"config":"Firefox 1024 - centered","suite":"searxng.spec.js","test_case":"search_code","attachments":[{"uid":"487a1eb07229eea1","name":"search_code","source":"487a1eb07229eea1.png","type":"image/png","size":155588},{"uid":"d75e276e2802f0e1","name":"search_code_console","source":"d75e276e2802f0e1.json","type":"application/json","size":2,"content":[]}]},{"config":"Firefox 1024 - centered","suite":"searxng.spec.js","test_case":"about","attachments":[{"uid":"11589ee17e7eac45","name":"about","source":"11589ee17e7eac45.png","type":"image/png","size":161346},{"uid":"cb5a0353f560d34d","name":"about_console","source":"cb5a0353f560d34d.json","type":"application/json","size":2,"content":[]}]},{"config":"Firefox 1024 - centered - rtl","suite":"searxng.spec.js","test_case":"preferences","attachments":[{"uid":"9606a94271ada049","name":"preferences-כללי","source":"9606a94271ada049.png","type":"image/png","size":74956},{"uid":"2fed568f05880ff6","name":"preferences-ממשק משתמש","source":"2fed568f05880ff6.png","type":"image/png","size":75776},{"uid":"a68ba17a347a9e6","name":"preferences-פרטיות","source":"a68ba17a347a9e6.png","type":"image/png","size":81705},{"uid":"5af59032176c884d","name":"preferences-מנועים","source":"5af59032176c884d.png","type":"image/png","size":68739},{"uid":"2a32c3b7c0c36f2e","name":"preferences-שאילתות מיוחדות","source":"2a32c3b7c0c36f2e.png","type":"image/png","size":98638},{"uid":"59073241dc46dfc3","name":"preferences-עוגיות","source":"59073241dc46dfc3.png","type":"image/png","size":94186},{"uid":"87241f2b0444e494","name":"preferences_console","source":"87241f2b0444e494.json","type":"application/json","size":2,"content":[]}]},{"config":"Firefox 1024 - centered - rtl","suite":"searxng.spec.js","test_case":"index","attachments":[{"uid":"ccbd847fee3de970","name":"index","source":"ccbd847fee3de970.png","type":"image/png","size":56131},{"uid":"7801c022b8071d82","name":"index_autocomplete","source":"7801c022b8071d82.png","type":"image/png","size":55251},{"uid":"543150b0bb3aa1b9","name":"index_console","source":"543150b0bb3aa1b9.json","type":"application/json","size":2,"content":[]}]},{"config":"Firefox 1024 - centered - rtl","suite":"searxng.spec.js","test_case":"search_general","attachments":[{"uid":"3bc0b8174df96c2f","name":"search_general","source":"3bc0b8174df96c2f.png","type":"image/png","size":141786},{"uid":"270b18d4a6256f48","name":"search_general_2","source":"270b18d4a6256f48.png","type":"image/png","size":135778},{"uid":"761049b85d2de34b","name":"search_general_console","source":"761049b85d2de34b.json","type":"application/json","size":2,"content":[]}]},{"config":"Firefox 1024 - centered - rtl","suite":"searxng.spec.js","test_case":"search_images","attachments":[{"uid":"50f4646ba9627cc0","name":"search_images","source":"50f4646ba9627cc0.png","type":"image/png","size":805748},{"uid":"1f918d062bf65b98","name":"search_images_detail","source":"1f918d062bf65b98.png","type":"image/png","size":432881},{"uid":"5cba3d61377cc449","name":"search_images_console","source":"5cba3d61377cc449.json","type":"application/json","size":2,"content":[]}]},{"config":"Firefox 1024 - centered - rtl","suite":"searxng.spec.js","test_case":"search_videos","attachments":[{"uid":"5b658f65dba771ac","name":"search_videos","source":"5b658f65dba771ac.png","type":"image/png","size":167630},{"uid":"176cb7997bb00a97","name":"search_videos_player","source":"176cb7997bb00a97.png","type":"image/png","size":187192},{"uid":"7ceed803fa91436f","name":"search_videos_console","source":"7ceed803fa91436f.json","type":"application/json","size":471,"content":[{"type":"warn","text":"[JavaScript Warning: \"Cookie “LAST_RESULT_ENTRY_KEY” will be soon rejected because it has the “SameSite” attribute set to “None” or an invalid value, without the “secure” attribute. To know more about the “SameSite“ attribute, read https://developer.mozilla.org/docs/Web/HTTP/Headers/Set-Cookie/SameSite\" {file: \"https://www.youtube-nocookie.com/s/player/c8b8a173/www-embed-player.vflset/www-embed-player.js\" line: 462}]"}]}]},{"config":"Firefox 1024 - centered - rtl","suite":"searxng.spec.js","test_case":"search_map","attachments":[{"uid":"bf01223d330e206","name":"search_map","source":"bf01223d330e206.png","type":"image/png","size":134769},{"uid":"4279ebdca492a18b","name":"search_map_detail","source":"4279ebdca492a18b.png","type":"image/png","size":425174},{"uid":"6fc2fe0e1c7bde5d","name":"search_map_console","source":"6fc2fe0e1c7bde5d.json","type":"application/json","size":2,"content":[]}]},{"config":"Firefox 1024 - centered - rtl","suite":"searxng.spec.js","test_case":"search_code","attachments":[{"uid":"5d4769e8e52a92da","name":"search_code","source":"5d4769e8e52a92da.png","type":"image/png","size":152744},{"uid":"1c7a60cc4151d9c4","name":"search_code_console","source":"1c7a60cc4151d9c4.json","type":"application/json","size":2,"content":[]}]},{"config":"Firefox 1024 - centered - rtl","suite":"searxng.spec.js","test_case":"about","attachments":[{"uid":"ebc090633e9c9f8d","name":"about","source":"ebc090633e9c9f8d.png","type":"image/png","size":162502},{"uid":"2c40d5b3a9681f46","name":"about_console","source":"2c40d5b3a9681f46.json","type":"application/json","size":2,"content":[]}]},{"config":"Mobile Chrome - centered","suite":"searxng.spec.js","test_case":"preferences","attachments":[{"uid":"a82a11da6b3b2118","name":"preferences-General","source":"a82a11da6b3b2118.png","type":"image/png","size":159415},{"uid":"4136bf70c88b5252","name":"preferences-User interface","source":"4136bf70c88b5252.png","type":"image/png","size":146828},{"uid":"ced5dad17313863e","name":"preferences-Privacy","source":"ced5dad17313863e.png","type":"image/png","size":170468},{"uid":"c3ca7a1fad016858","name":"preferences-Engines","source":"c3ca7a1fad016858.png","type":"image/png","size":118046},{"uid":"22660a57177c295d","name":"preferences-Special Queries","source":"22660a57177c295d.png","type":"image/png","size":168487},{"uid":"345627af3fe9447b","name":"preferences-Cookies","source":"345627af3fe9447b.png","type":"image/png","size":227155},{"uid":"606a2fc5bfdacef6","name":"preferences_console","source":"606a2fc5bfdacef6.json","type":"application/json","size":2,"content":[]}]},{"config":"Mobile Chrome - centered","suite":"searxng.spec.js","test_case":"index","attachments":[{"uid":"e43ca914934f9c48","name":"index","source":"e43ca914934f9c48.png","type":"image/png","size":122748},{"uid":"2bbde014d0230ee1","name":"index_autocomplete","source":"2bbde014d0230ee1.png","type":"image/png","size":16688},{"uid":"5fd6ae631d805b3","name":"index_console","source":"5fd6ae631d805b3.json","type":"application/json","size":2,"content":[]}]},{"config":"Mobile Chrome - centered","suite":"searxng.spec.js","test_case":"search_general","attachments":[{"uid":"fbf1d39c7c274480","name":"search_general","source":"fbf1d39c7c274480.png","type":"image/png","size":793807},{"uid":"b8677e100149228e","name":"search_general_2","source":"b8677e100149228e.png","type":"image/png","size":355117},{"uid":"6ca0864b32be85d3","name":"search_general_console","source":"6ca0864b32be85d3.json","type":"application/json","size":2,"content":[]}]},{"config":"Mobile Chrome - centered","suite":"searxng.spec.js","test_case":"search_images","attachments":[{"uid":"f4446b57fe300814","name":"search_images","source":"f4446b57fe300814.png","type":"image/png","size":1528367},{"uid":"83107212e6bee514","name":"search_images_detail","source":"83107212e6bee514.png","type":"image/png","size":712199},{"uid":"3a2beb0c60069271","name":"search_images_console","source":"3a2beb0c60069271.json","type":"application/json","size":2,"content":[]}]},{"config":"Mobile Chrome - centered","suite":"searxng.spec.js","test_case":"search_videos","attachments":[{"uid":"fce38dd27d146654","name":"search_videos","source":"fce38dd27d146654.png","type":"image/png","size":361675},{"uid":"6c5932159ec097c5","name":"search_videos_player","source":"6c5932159ec097c5.png","type":"image/png","size":360348},{"uid":"c13a3229038efcfd","name":"search_videos_console","source":"c13a3229038efcfd.json","type":"application/json","size":2,"content":[]}]},{"config":"Mobile Chrome - centered","suite":"searxng.spec.js","test_case":"search_map","attachments":[{"uid":"fda9d88eb8ad429","name":"search_map","source":"fda9d88eb8ad429.png","type":"image/png","size":457528},{"uid":"ecefca3b3ef7e709","name":"search_map_detail","source":"ecefca3b3ef7e709.png","type":"image/png","size":1410516},{"uid":"38c51b580ad1d9a4","name":"search_map_console","source":"38c51b580ad1d9a4.json","type":"application/json","size":2,"content":[]}]},{"config":"Mobile Chrome - centered","suite":"searxng.spec.js","test_case":"search_code","attachments":[{"uid":"454c50050ca5db20","name":"search_code","source":"454c50050ca5db20.png","type":"image/png","size":381519},{"uid":"213349f2899ad430","name":"search_code_console","source":"213349f2899ad430.json","type":"application/json","size":2,"content":[]}]},{"config":"Mobile Chrome - centered","suite":"searxng.spec.js","test_case":"about","attachments":[{"uid":"58639b56611ed241","name":"about","source":"58639b56611ed241.png","type":"image/png","size":428098},{"uid":"32f745305b036287","name":"about_console","source":"32f745305b036287.json","type":"application/json","size":2,"content":[]}]},{"config":"Mobile Chrome - centered - rtl","suite":"searxng.spec.js","test_case":"preferences","attachments":[{"uid":"b0f25ce3e3299ac1","name":"preferences-כללי","source":"b0f25ce3e3299ac1.png","type":"image/png","size":98895},{"uid":"c5512d1c0f660d08","name":"preferences-ממשק משתמש","source":"c5512d1c0f660d08.png","type":"image/png","size":106788},{"uid":"48b282cda39b2187","name":"preferences-פרטיות","source":"48b282cda39b2187.png","type":"image/png","size":118362},{"uid":"91001aeca100f5cc","name":"preferences-מנועים","source":"91001aeca100f5cc.png","type":"image/png","size":35708},{"uid":"e31c5a85153a3879","name":"preferences-שאילתות מיוחדות","source":"e31c5a85153a3879.png","type":"image/png","size":121371},{"uid":"77181a5cda59116d","name":"preferences-עוגיות","source":"77181a5cda59116d.png","type":"image/png","size":170041},{"uid":"eea5ac127abead21","name":"preferences_console","source":"eea5ac127abead21.json","type":"application/json","size":2,"content":[]}]},{"config":"Mobile Chrome - centered - rtl","suite":"searxng.spec.js","test_case":"index","attachments":[{"uid":"364f5acc4512d12e","name":"index","source":"364f5acc4512d12e.png","type":"image/png","size":111712},{"uid":"be54dddd45ef7bd4","name":"index_autocomplete","source":"be54dddd45ef7bd4.png","type":"image/png","size":16747},{"uid":"8024753820385e75","name":"index_console","source":"8024753820385e75.json","type":"application/json","size":2,"content":[]}]},{"config":"Mobile Chrome - centered - rtl","suite":"searxng.spec.js","test_case":"search_general","attachments":[{"uid":"3bd3e4830628a3b7","name":"search_general","source":"3bd3e4830628a3b7.png","type":"image/png","size":473533},{"uid":"567c3633964cc078","name":"search_general_2","source":"567c3633964cc078.png","type":"image/png","size":333327},{"uid":"4005f5b82afa5dc3","name":"search_general_console","source":"4005f5b82afa5dc3.json","type":"application/json","size":2,"content":[]}]},{"config":"Mobile Chrome - centered - rtl","suite":"searxng.spec.js","test_case":"search_images","attachments":[{"uid":"9baef9558969e04f","name":"search_images","source":"9baef9558969e04f.png","type":"image/png","size":1523808},{"uid":"33bf2de63c51dae1","name":"search_images_detail","source":"33bf2de63c51dae1.png","type":"image/png","size":707030},{"uid":"5cf61d64faf53651","name":"search_images_console","source":"5cf61d64faf53651.json","type":"application/json","size":2,"content":[]}]},{"config":"Mobile Chrome - centered - rtl","suite":"searxng.spec.js","test_case":"search_videos","attachments":[{"uid":"d590bede48f9f845","name":"search_videos","source":"d590bede48f9f845.png","type":"image/png","size":324134},{"uid":"7d0ed5f205babc7f","name":"search_videos_player","source":"7d0ed5f205babc7f.png","type":"image/png","size":378164},{"uid":"d560698490a22463","name":"search_videos_console","source":"d560698490a22463.json","type":"application/json","size":2,"content":[]}]},{"config":"Mobile Chrome - centered - rtl","suite":"searxng.spec.js","test_case":"search_map","attachments":[{"uid":"6d01adb382f4e521","name":"search_map","source":"6d01adb382f4e521.png","type":"image/png","size":414290},{"uid":"a9fa66a57cdd9f5a","name":"search_map_detail","source":"a9fa66a57cdd9f5a.png","type":"image/png","size":1380510},{"uid":"17a642d810a777f5","name":"search_map_console","source":"17a642d810a777f5.json","type":"application/json","size":2,"content":[]}]},{"config":"Mobile Chrome - centered - rtl","suite":"searxng.spec.js","test_case":"search_code","attachments":[{"uid":"d1ef2ec766fb6a60","name":"search_code","source":"d1ef2ec766fb6a60.png","type":"image/png","size":358701},{"uid":"4ea2721c165e444d","name":"search_code_console","source":"4ea2721c165e444d.json","type":"application/json","size":2,"content":[]}]},{"config":"Mobile Chrome - centered - rtl","suite":"searxng.spec.js","test_case":"about","attachments":[{"uid":"2eeb388f500e7d0e","name":"about","source":"2eeb388f500e7d0e.png","type":"image/png","size":155689},{"uid":"53fea2a8dddd9dbb","name":"about_console","source":"53fea2a8dddd9dbb.json","type":"application/json","size":2,"content":[]}]},{"config":"Firefox 1920 - rtl","suite":"searxng.spec.js","test_case":"preferences","attachments":[{"uid":"e7145040a04f778a","name":"preferences-כללי","source":"e7145040a04f778a.png","type":"image/png","size":124165},{"uid":"826a263e03279d4e","name":"preferences-ממשק משתמש","source":"826a263e03279d4e.png","type":"image/png","size":129259},{"uid":"15bc3a1b84f0ffb","name":"preferences-פרטיות","source":"15bc3a1b84f0ffb.png","type":"image/png","size":107166},{"uid":"129ac2773da9163","name":"preferences-מנועים","source":"129ac2773da9163.png","type":"image/png","size":115032},{"uid":"b40d8480bc5bd528","name":"preferences-שאילתות מיוחדות","source":"b40d8480bc5bd528.png","type":"image/png","size":143263},{"uid":"4af976d6ff2572cd","name":"preferences-עוגיות","source":"4af976d6ff2572cd.png","type":"image/png","size":138567},{"uid":"d57cf938a564d159","name":"preferences_console","source":"d57cf938a564d159.json","type":"application/json","size":2,"content":[]}]},{"config":"Firefox 1920 - rtl","suite":"searxng.spec.js","test_case":"index","attachments":[{"uid":"3d4b2f337b17235c","name":"index","source":"3d4b2f337b17235c.png","type":"image/png","size":84982},{"uid":"3a9588219b251d18","name":"index_autocomplete","source":"3a9588219b251d18.png","type":"image/png","size":84120},{"uid":"b7ddd59113c94498","name":"index_console","source":"b7ddd59113c94498.json","type":"application/json","size":2,"content":[]}]},{"config":"Firefox 1920 - rtl","suite":"searxng.spec.js","test_case":"search_general","attachments":[{"uid":"955a2301c7f655d9","name":"search_general","source":"955a2301c7f655d9.png","type":"image/png","size":327079},{"uid":"fbe6f3d0bc804d69","name":"search_general_2","source":"fbe6f3d0bc804d69.png","type":"image/png","size":219677},{"uid":"b0fe06b1e6d24a23","name":"search_general_console","source":"b0fe06b1e6d24a23.json","type":"application/json","size":2,"content":[]}]},{"config":"Firefox 1920 - rtl","suite":"searxng.spec.js","test_case":"search_images","attachments":[{"uid":"79e99a37ac979941","name":"search_images","source":"79e99a37ac979941.png","type":"image/png","size":2264561},{"uid":"2ab320b271786ede","name":"search_images_detail","source":"2ab320b271786ede.png","type":"image/png","size":1828949},{"uid":"61b7e5419e26ac03","name":"search_images_console","source":"61b7e5419e26ac03.json","type":"application/json","size":2,"content":[]}]},{"config":"Firefox 1920 - rtl","suite":"searxng.spec.js","test_case":"search_videos","attachments":[{"uid":"769ce0fc1c913296","name":"search_videos","source":"769ce0fc1c913296.png","type":"image/png","size":300307},{"uid":"37b6c6ef112b13ac","name":"search_videos_player","source":"37b6c6ef112b13ac.png","type":"image/png","size":305891},{"uid":"430f63f70a916110","name":"search_videos_console","source":"430f63f70a916110.json","type":"application/json","size":471,"content":[{"type":"warn","text":"[JavaScript Warning: \"Cookie “LAST_RESULT_ENTRY_KEY” will be soon rejected because it has the “SameSite” attribute set to “None” or an invalid value, without the “secure” attribute. To know more about the “SameSite“ attribute, read https://developer.mozilla.org/docs/Web/HTTP/Headers/Set-Cookie/SameSite\" {file: \"https://www.youtube-nocookie.com/s/player/c8b8a173/www-embed-player.vflset/www-embed-player.js\" line: 462}]"}]}]},{"config":"Firefox 1920 - rtl","suite":"searxng.spec.js","test_case":"search_map","attachments":[{"uid":"f4a8ebd1091a2a7a","name":"search_map","source":"f4a8ebd1091a2a7a.png","type":"image/png","size":205704},{"uid":"a11ae32db075f5c7","name":"search_map_detail","source":"a11ae32db075f5c7.png","type":"image/png","size":508615},{"uid":"4011140fb3a52ac5","name":"search_map_console","source":"4011140fb3a52ac5.json","type":"application/json","size":2,"content":[]}]},{"config":"Firefox 1920 - rtl","suite":"searxng.spec.js","test_case":"search_code","attachments":[{"uid":"b8ca337c2239a8dd","name":"search_code","source":"b8ca337c2239a8dd.png","type":"image/png","size":249882},{"uid":"be26d617b20eb506","name":"search_code_console","source":"be26d617b20eb506.json","type":"application/json","size":2,"content":[]}]},{"config":"Firefox 1920 - rtl","suite":"searxng.spec.js","test_case":"about","attachments":[{"uid":"7e53d8515f529afe","name":"about","source":"7e53d8515f529afe.png","type":"image/png","size":240876},{"uid":"509ea78386d4d42","name":"about_console","source":"509ea78386d4d42.json","type":"application/json","size":2,"content":[]}]},{"config":"Firefox 1920 - no js","suite":"searxng.spec.js","test_case":"preferences","attachments":[{"uid":"cdcb3c971229d972","name":"preferences-General","source":"cdcb3c971229d972.png","type":"image/png","size":136768},{"uid":"444e9aed338097f7","name":"preferences-User interface","source":"444e9aed338097f7.png","type":"image/png","size":141400},{"uid":"c03c5cca5e9fbd9b","name":"preferences-Privacy","source":"c03c5cca5e9fbd9b.png","type":"image/png","size":115163},{"uid":"ba3a826fd631f6df","name":"preferences-Engines","source":"ba3a826fd631f6df.png","type":"image/png","size":124771},{"uid":"29ed084de030eae5","name":"preferences-Special Queries","source":"29ed084de030eae5.png","type":"image/png","size":153110},{"uid":"6d5c97e25d1e0d49","name":"preferences-Cookies","source":"6d5c97e25d1e0d49.png","type":"image/png","size":146703},{"uid":"6f29038ba820eed8","name":"preferences_console","source":"6f29038ba820eed8.json","type":"application/json","size":2,"content":[]}]},{"config":"Firefox 1920 - no js","suite":"searxng.spec.js","test_case":"index","attachments":[{"uid":"1605ea23b4f2ad67","name":"index","source":"1605ea23b4f2ad67.png","type":"image/png","size":86679},{"uid":"10c8103cf64510b9","name":"index_console","source":"10c8103cf64510b9.json","type":"application/json","size":2,"content":[]}]},{"config":"Firefox 1920 - no js","suite":"searxng.spec.js","test_case":"search_general","attachments":[{"uid":"8dab2a2f777217e0","name":"search_general","source":"8dab2a2f777217e0.png","type":"image/png","size":432922},{"uid":"7bd2492db6e7c86c","name":"search_general_console","source":"7bd2492db6e7c86c.json","type":"application/json","size":2,"content":[]}]},{"config":"Firefox 1920 - no js","suite":"searxng.spec.js","test_case":"search_images","attachments":[{"uid":"441828a728c76482","name":"search_images","source":"441828a728c76482.png","type":"image/png","size":2331568},{"uid":"a4fefcfda73c5cc8","name":"search_images_console","source":"a4fefcfda73c5cc8.json","type":"application/json","size":2,"content":[]}]},{"config":"Firefox 1920 - no js","suite":"searxng.spec.js","test_case":"search_videos","attachments":[{"uid":"3e7a1f5b696c5a2d","name":"search_videos","source":"3e7a1f5b696c5a2d.png","type":"image/png","size":361788},{"uid":"f3b6b8b3a783ce9b","name":"search_videos_console","source":"f3b6b8b3a783ce9b.json","type":"application/json","size":2,"content":[]}]},{"config":"Firefox 1920 - no js","suite":"searxng.spec.js","test_case":"search_map","attachments":[{"uid":"2e3e40f2a271068a","name":"search_map","source":"2e3e40f2a271068a.png","type":"image/png","size":206498},{"uid":"c5a7ee799b5a4f2e","name":"search_map_console","source":"c5a7ee799b5a4f2e.json","type":"application/json","size":2,"content":[]}]},{"config":"Firefox 1920 - no js","suite":"searxng.spec.js","test_case":"search_code","attachments":[{"uid":"4269f006859f29b","name":"search_code","source":"4269f006859f29b.png","type":"image/png","size":254647},{"uid":"d6725938a77832d0","name":"search_code_console","source":"d6725938a77832d0.json","type":"application/json","size":2,"content":[]}]},{"config":"Firefox 1920 - no js","suite":"searxng.spec.js","test_case":"about","attachments":[{"uid":"9f7f9828f181f6e3","name":"about","source":"9f7f9828f181f6e3.png","type":"image/png","size":241103},{"uid":"8c21190bd0c23a4a","name":"about_console","source":"8c21190bd0c23a4a.json","type":"application/json","size":2,"content":[]}]},{"config":"Firefox 1920 - dark mode","suite":"searxng.spec.js","test_case":"preferences","attachments":[{"uid":"799d6c6f65493b46","name":"preferences-General","source":"799d6c6f65493b46.png","type":"image/png","size":150863},{"uid":"7aba6d530e5b00fb","name":"preferences-User interface","source":"7aba6d530e5b00fb.png","type":"image/png","size":156328},{"uid":"99daef95c305686a","name":"preferences-Privacy","source":"99daef95c305686a.png","type":"image/png","size":126076},{"uid":"8225820048ce16d9","name":"preferences-Engines","source":"8225820048ce16d9.png","type":"image/png","size":135393},{"uid":"8eab205798dfed6b","name":"preferences-Special Queries","source":"8eab205798dfed6b.png","type":"image/png","size":171927},{"uid":"3afd0cec759262ab","name":"preferences-Cookies","source":"3afd0cec759262ab.png","type":"image/png","size":164551},{"uid":"be69bcffa3402963","name":"preferences_console","source":"be69bcffa3402963.json","type":"application/json","size":2,"content":[]}]},{"config":"Firefox 1920 - dark mode","suite":"searxng.spec.js","test_case":"index","attachments":[{"uid":"2e781e067f3ca16c","name":"index","source":"2e781e067f3ca16c.png","type":"image/png","size":90669},{"uid":"1e428daef972580a","name":"index_autocomplete","source":"1e428daef972580a.png","type":"image/png","size":89468},{"uid":"388107d5a2610ff","name":"index_console","source":"388107d5a2610ff.json","type":"application/json","size":2,"content":[]}]},{"config":"Firefox 1920 - dark mode","suite":"searxng.spec.js","test_case":"search_general","attachments":[{"uid":"65347a55577baca3","name":"search_general","source":"65347a55577baca3.png","type":"image/png","size":469307},{"uid":"a883f82fdc53c0b6","name":"search_general_2","source":"a883f82fdc53c0b6.png","type":"image/png","size":232979},{"uid":"a26743d0aa7bb229","name":"search_general_console","source":"a26743d0aa7bb229.json","type":"application/json","size":2,"content":[]}]},{"config":"Firefox 1920 - dark mode","suite":"searxng.spec.js","test_case":"search_images","attachments":[{"uid":"3ae4921ca03c3295","name":"search_images","source":"3ae4921ca03c3295.png","type":"image/png","size":2309792},{"uid":"dc9af82bad624834","name":"search_images_detail","source":"dc9af82bad624834.png","type":"image/png","size":1864618},{"uid":"27dc41b730430d07","name":"search_images_console","source":"27dc41b730430d07.json","type":"application/json","size":2,"content":[]}]},{"config":"Firefox 1920 - dark mode","suite":"searxng.spec.js","test_case":"search_videos","attachments":[{"uid":"87b2d50fca655908","name":"search_videos","source":"87b2d50fca655908.png","type":"image/png","size":347300},{"uid":"83be8f99d1a7b239","name":"search_videos_player","source":"83be8f99d1a7b239.png","type":"image/png","size":342207},{"uid":"e03022537866234","name":"search_videos_console","source":"e03022537866234.json","type":"application/json","size":1840,"content":[{"type":"warn","text":"[JavaScript Warning: \"Cookie “LAST_RESULT_ENTRY_KEY” will be soon rejected because it has the “SameSite” attribute set to “None” or an invalid value, without the “secure” attribute. To know more about the “SameSite“ attribute, read https://developer.mozilla.org/docs/Web/HTTP/Headers/Set-Cookie/SameSite\" {file: \"https://www.youtube-nocookie.com/s/player/c8b8a173/www-embed-player.vflset/www-embed-player.js\" line: 462}]"},{"type":"warn","text":"[JavaScript Warning: \"Cookie “nextId” will be soon rejected because it has the “SameSite” attribute set to “None” or an invalid value, without the “secure” attribute. To know more about the “SameSite“ attribute, read https://developer.mozilla.org/docs/Web/HTTP/Headers/Set-Cookie/SameSite\" {file: \"https://www.youtube-nocookie.com/s/player/c8b8a173/www-embed-player.vflset/www-embed-player.js\" line: 462}]"},{"type":"warn","text":"[JavaScript Warning: \"Cookie “requests” will be soon rejected because it has the “SameSite” attribute set to “None” or an invalid value, without the “secure” attribute. To know more about the “SameSite“ attribute, read https://developer.mozilla.org/docs/Web/HTTP/Headers/Set-Cookie/SameSite\" {file: \"https://www.youtube-nocookie.com/s/player/c8b8a173/www-embed-player.vflset/www-embed-player.js\" line: 462}]"},{"type":"warn","text":"[JavaScript Warning: \"Cookie “requests” will be soon rejected because it has the “SameSite” attribute set to “None” or an invalid value, without the “secure” attribute. To know more about the “SameSite“ attribute, read https://developer.mozilla.org/docs/Web/HTTP/Headers/Set-Cookie/SameSite\" {file: \"https://www.youtube-nocookie.com/s/player/c8b8a173/www-embed-player.vflset/www-embed-player.js\" line: 462}]"}]}]},{"config":"Firefox 1920 - dark mode","suite":"searxng.spec.js","test_case":"search_map","attachments":[{"uid":"bb44f1ad3a6ed829","name":"search_map","source":"bb44f1ad3a6ed829.png","type":"image/png","size":227005},{"uid":"92982462cd6db3ed","name":"search_map_detail","source":"92982462cd6db3ed.png","type":"image/png","size":523829},{"uid":"47aadd4cb2106d19","name":"search_map_console","source":"47aadd4cb2106d19.json","type":"application/json","size":2,"content":[]}]},{"config":"Firefox 1920 - dark mode","suite":"searxng.spec.js","test_case":"search_code","attachments":[{"uid":"f98923a1809faf98","name":"search_code","source":"f98923a1809faf98.png","type":"image/png","size":253531},{"uid":"94f78ecb5d40cfee","name":"search_code_console","source":"94f78ecb5d40cfee.json","type":"application/json","size":2,"content":[]}]},{"config":"Firefox 1920 - dark mode","suite":"searxng.spec.js","test_case":"about","attachments":[{"uid":"a12e923c2fe23641","name":"about","source":"a12e923c2fe23641.png","type":"image/png","size":268627},{"uid":"870cb275296fdc1","name":"about_console","source":"870cb275296fdc1.json","type":"application/json","size":2,"content":[]}]},{"config":"Chrome 1920 - high contrast","suite":"searxng.spec.js","test_case":"preferences","attachments":[{"uid":"f09de7135d18abff","name":"preferences-General","source":"f09de7135d18abff.png","type":"image/png","size":115090},{"uid":"b6f71424b4a58f2a","name":"preferences-User interface","source":"b6f71424b4a58f2a.png","type":"image/png","size":116617},{"uid":"8503ef1ff811b2ee","name":"preferences-Privacy","source":"8503ef1ff811b2ee.png","type":"image/png","size":90572},{"uid":"d46caa8d0c9db057","name":"preferences-Engines","source":"d46caa8d0c9db057.png","type":"image/png","size":90199},{"uid":"5ba15afc332134f3","name":"preferences-Special Queries","source":"5ba15afc332134f3.png","type":"image/png","size":132000},{"uid":"f5f8c6765e70d23","name":"preferences-Cookies","source":"f5f8c6765e70d23.png","type":"image/png","size":128426},{"uid":"23b8f5466c91083d","name":"preferences_console","source":"23b8f5466c91083d.json","type":"application/json","size":2,"content":[]}]},{"config":"Chrome 1920 - high contrast","suite":"searxng.spec.js","test_case":"index","attachments":[{"uid":"67d5c5790812af3b","name":"index","source":"67d5c5790812af3b.png","type":"image/png","size":43537},{"uid":"3cd2ac201cc3ad72","name":"index_autocomplete","source":"3cd2ac201cc3ad72.png","type":"image/png","size":42464},{"uid":"528b423097b0e367","name":"index_console","source":"528b423097b0e367.json","type":"application/json","size":2,"content":[]}]},{"config":"Chrome 1920 - high contrast","suite":"searxng.spec.js","test_case":"search_general","attachments":[{"uid":"bef59be7826a48c0","name":"search_general","source":"bef59be7826a48c0.png","type":"image/png","size":393457},{"uid":"e5549a3be9ff9a22","name":"search_general_2","source":"e5549a3be9ff9a22.png","type":"image/png","size":203536},{"uid":"f2ccdc05dad7c310","name":"search_general_console","source":"f2ccdc05dad7c310.json","type":"application/json","size":2,"content":[]}]},{"config":"Chrome 1920 - high contrast","suite":"searxng.spec.js","test_case":"search_images","attachments":[{"uid":"4274719d33d7dc34","name":"search_images","source":"4274719d33d7dc34.png","type":"image/png","size":2127341},{"uid":"1785de479666a965","name":"search_images_detail","source":"1785de479666a965.png","type":"image/png","size":1497142},{"uid":"5ea984b0ae325621","name":"search_images_console","source":"5ea984b0ae325621.json","type":"application/json","size":2,"content":[]}]},{"config":"Chrome 1920 - high contrast","suite":"searxng.spec.js","test_case":"search_videos","attachments":[{"uid":"e85ae7eaccb15dbc","name":"search_videos","source":"e85ae7eaccb15dbc.png","type":"image/png","size":305119},{"uid":"bb994fca135c9233","name":"search_videos_player","source":"bb994fca135c9233.png","type":"image/png","size":276331},{"uid":"76d1393147248c65","name":"search_videos_console","source":"76d1393147248c65.json","type":"application/json","size":2,"content":[]}]},{"config":"Chrome 1920 - high contrast","suite":"searxng.spec.js","test_case":"search_map","attachments":[{"uid":"bb3d27d2ab4d0105","name":"search_map","source":"bb3d27d2ab4d0105.png","type":"image/png","size":173765},{"uid":"a6a5026429570ade","name":"search_map_detail","source":"a6a5026429570ade.png","type":"image/png","size":470021},{"uid":"9cd722d71a491f63","name":"search_map_console","source":"9cd722d71a491f63.json","type":"application/json","size":2,"content":[]}]},{"config":"Chrome 1920 - high contrast","suite":"searxng.spec.js","test_case":"search_code","attachments":[{"uid":"908d40ec44bf8815","name":"search_code","source":"908d40ec44bf8815.png","type":"image/png","size":222666},{"uid":"12776bc33859b51d","name":"search_code_console","source":"12776bc33859b51d.json","type":"application/json","size":2,"content":[]}]},{"config":"Chrome 1920 - high contrast","suite":"searxng.spec.js","test_case":"about","attachments":[{"uid":"245a1cbaef8ed61b","name":"about","source":"245a1cbaef8ed61b.png","type":"image/png","size":223349},{"uid":"3139e434806c6379","name":"about_console","source":"3139e434806c6379.json","type":"application/json","size":2,"content":[]}]},{"config":"Webkit 1920","suite":"searxng.spec.js","test_case":"preferences","attachments":[{"uid":"d93be7a289992e72","name":"preferences-General","source":"d93be7a289992e72.png","type":"image/png","size":218631},{"uid":"57e53ffbdd2d4165","name":"preferences-User interface","source":"57e53ffbdd2d4165.png","type":"image/png","size":216371},{"uid":"8d4d9b005cd4273e","name":"preferences-Privacy","source":"8d4d9b005cd4273e.png","type":"image/png","size":170226},{"uid":"8187668dd20e2544","name":"preferences-Engines","source":"8187668dd20e2544.png","type":"image/png","size":185960},{"uid":"68cff5c008a5a5bf","name":"preferences-Special Queries","source":"68cff5c008a5a5bf.png","type":"image/png","size":230354},{"uid":"f6c04fab0a3b4ff4","name":"preferences-Cookies","source":"f6c04fab0a3b4ff4.png","type":"image/png","size":208286},{"uid":"f9e2381dad2db90a","name":"preferences_console","source":"f9e2381dad2db90a.json","type":"application/json","size":2,"content":[]}]},{"config":"Webkit 1920","suite":"searxng.spec.js","test_case":"index","attachments":[{"uid":"10c72881f24341f2","name":"index","source":"10c72881f24341f2.png","type":"image/png","size":103305},{"uid":"aa9d3d0df9f570a0","name":"index_autocomplete","source":"aa9d3d0df9f570a0.png","type":"image/png","size":101245},{"uid":"ace56933f2b7b797","name":"index_console","source":"ace56933f2b7b797.json","type":"application/json","size":2,"content":[]}]},{"config":"Webkit 1920","suite":"searxng.spec.js","test_case":"search_general","attachments":[{"uid":"84ae4db6dcf23854","name":"search_general","source":"84ae4db6dcf23854.png","type":"image/png","size":875196},{"uid":"1adadcd141b7bddd","name":"search_general_2","source":"1adadcd141b7bddd.png","type":"image/png","size":322869},{"uid":"8d2c45b905a487d3","name":"search_general_console","source":"8d2c45b905a487d3.json","type":"application/json","size":2,"content":[]}]},{"config":"Webkit 1920","suite":"searxng.spec.js","test_case":"search_images","attachments":[{"uid":"b05a7162191cff32","name":"search_images","source":"b05a7162191cff32.png","type":"image/png","size":1922314},{"uid":"6ee0ea2ce9714550","name":"search_images_detail","source":"6ee0ea2ce9714550.png","type":"image/png","size":1649524},{"uid":"f94529ccc32ebaae","name":"search_images_console","source":"f94529ccc32ebaae.json","type":"application/json","size":2,"content":[]}]},{"config":"Webkit 1920","suite":"searxng.spec.js","test_case":"search_videos","attachments":[{"uid":"b34140251cda6a03","name":"search_videos","source":"b34140251cda6a03.png","type":"image/png","size":636773},{"uid":"20ea23d9c96c5fcc","name":"search_videos_player","source":"20ea23d9c96c5fcc.png","type":"image/png","size":613080},{"uid":"742a62c9d398e793","name":"search_videos_console","source":"742a62c9d398e793.json","type":"application/json","size":2,"content":[]}]},{"config":"Webkit 1920","suite":"searxng.spec.js","test_case":"search_map","attachments":[{"uid":"9f11d608d2fc1c16","name":"search_map","source":"9f11d608d2fc1c16.png","type":"image/png","size":406979},{"uid":"4fbe92bb622a35b5","name":"search_map_detail","source":"4fbe92bb622a35b5.png","type":"image/png","size":732562},{"uid":"fec5d8b6d5e0fee3","name":"search_map_console","source":"fec5d8b6d5e0fee3.json","type":"application/json","size":2,"content":[]}]},{"config":"Webkit 1920","suite":"searxng.spec.js","test_case":"search_code","attachments":[{"uid":"b3a0dfdc6a6525fa","name":"search_code","source":"b3a0dfdc6a6525fa.png","type":"image/png","size":424010},{"uid":"7bb7f88bdcc7bc82","name":"search_code_console","source":"7bb7f88bdcc7bc82.json","type":"application/json","size":2,"content":[]}]},{"config":"Webkit 1920","suite":"searxng.spec.js","test_case":"about","attachments":[{"uid":"3ad676eecdadc47a","name":"about","source":"3ad676eecdadc47a.png","type":"image/png","size":351803},{"uid":"bdd1559ec8ab2ca2","name":"about_console","source":"bdd1559ec8ab2ca2.json","type":"application/json","size":2,"content":[]}]},{"config":"Mobile Chrome","suite":"searxng.spec.js","test_case":"preferences","attachments":[{"uid":"c4277cc5476e6bf7","name":"preferences-General","source":"c4277cc5476e6bf7.png","type":"image/png","size":159415},{"uid":"d471f994aed89a0b","name":"preferences-User interface","source":"d471f994aed89a0b.png","type":"image/png","size":146828},{"uid":"85c82136127311f3","name":"preferences-Privacy","source":"85c82136127311f3.png","type":"image/png","size":170468},{"uid":"e115b9c024a53ac7","name":"preferences-Engines","source":"e115b9c024a53ac7.png","type":"image/png","size":118046},{"uid":"d3b55395f5416161","name":"preferences-Special Queries","source":"d3b55395f5416161.png","type":"image/png","size":168487},{"uid":"954b003f4ddb13ad","name":"preferences-Cookies","source":"954b003f4ddb13ad.png","type":"image/png","size":235771},{"uid":"febd56bf90fa5c4f","name":"preferences_console","source":"febd56bf90fa5c4f.json","type":"application/json","size":2,"content":[]}]},{"config":"Mobile Chrome","suite":"searxng.spec.js","test_case":"index","attachments":[{"uid":"3e1ea1bcf04b1a56","name":"index","source":"3e1ea1bcf04b1a56.png","type":"image/png","size":122748},{"uid":"a2d89d1d9fd88f64","name":"index_autocomplete","source":"a2d89d1d9fd88f64.png","type":"image/png","size":16688},{"uid":"789fc1777c32769f","name":"index_console","source":"789fc1777c32769f.json","type":"application/json","size":2,"content":[]}]},{"config":"Mobile Chrome","suite":"searxng.spec.js","test_case":"search_general","attachments":[{"uid":"cc321860f332573","name":"search_general","source":"cc321860f332573.png","type":"image/png","size":801954},{"uid":"29bbd64bd570b585","name":"search_general_2","source":"29bbd64bd570b585.png","type":"image/png","size":354561},{"uid":"3931edce19f8b884","name":"search_general_console","source":"3931edce19f8b884.json","type":"application/json","size":2,"content":[]}]},{"config":"Mobile Chrome","suite":"searxng.spec.js","test_case":"search_images","attachments":[{"uid":"7a309d4e0bb9b000","name":"search_images","source":"7a309d4e0bb9b000.png","type":"image/png","size":1394607},{"uid":"482861513cc13f15","name":"search_images_detail","source":"482861513cc13f15.png","type":"image/png","size":712199},{"uid":"59e3166c19445dad","name":"search_images_console","source":"59e3166c19445dad.json","type":"application/json","size":2,"content":[]}]},{"config":"Mobile Chrome","suite":"searxng.spec.js","test_case":"search_videos","attachments":[{"uid":"fe9da4aa9c672b6","name":"search_videos","source":"fe9da4aa9c672b6.png","type":"image/png","size":361675},{"uid":"dd54b9d3cfe52d36","name":"search_videos_player","source":"dd54b9d3cfe52d36.png","type":"image/png","size":360348},{"uid":"8f831f82ca31fb","name":"search_videos_console","source":"8f831f82ca31fb.json","type":"application/json","size":2,"content":[]}]},{"config":"Mobile Chrome","suite":"searxng.spec.js","test_case":"search_map","attachments":[{"uid":"69061b03cc8994f7","name":"search_map","source":"69061b03cc8994f7.png","type":"image/png","size":457528},{"uid":"46452cf2abdb9707","name":"search_map_detail","source":"46452cf2abdb9707.png","type":"image/png","size":1410516},{"uid":"21051239f00c0315","name":"search_map_console","source":"21051239f00c0315.json","type":"application/json","size":2,"content":[]}]},{"config":"Mobile Chrome","suite":"searxng.spec.js","test_case":"search_code","attachments":[{"uid":"be026d1613c7408c","name":"search_code","source":"be026d1613c7408c.png","type":"image/png","size":381519},{"uid":"986feb74af416e3f","name":"search_code_console","source":"986feb74af416e3f.json","type":"application/json","size":2,"content":[]}]},{"config":"Mobile Chrome","suite":"searxng.spec.js","test_case":"about","attachments":[{"uid":"2b97b0ce67d908d0","name":"about","source":"2b97b0ce67d908d0.png","type":"image/png","size":428098},{"uid":"57ce2852fab16e8a","name":"about_console","source":"57ce2852fab16e8a.json","type":"application/json","size":2,"content":[]}]},{"config":"Mobile Safari","suite":"searxng.spec.js","test_case":"preferences","attachments":[{"uid":"6ecbdf2b7c5ea285","name":"preferences-General","source":"6ecbdf2b7c5ea285.png","type":"image/png","size":133263},{"uid":"7147269aee736e98","name":"preferences-User interface","source":"7147269aee736e98.png","type":"image/png","size":114590},{"uid":"6be1255e8b4f28ec","name":"preferences-Privacy","source":"6be1255e8b4f28ec.png","type":"image/png","size":136723},{"uid":"f294c4f231b40ed","name":"preferences-Engines","source":"f294c4f231b40ed.png","type":"image/png","size":101053},{"uid":"bb2011f618669836","name":"preferences-Special Queries","source":"bb2011f618669836.png","type":"image/png","size":115069},{"uid":"1ab9608658ba70b0","name":"preferences-Cookies","source":"1ab9608658ba70b0.png","type":"image/png","size":169709},{"uid":"cc0baaefe5507302","name":"preferences_console","source":"cc0baaefe5507302.json","type":"application/json","size":2,"content":[]}]},{"config":"Mobile Safari","suite":"searxng.spec.js","test_case":"index","attachments":[{"uid":"1fd30d4f375c585b","name":"index","source":"1fd30d4f375c585b.png","type":"image/png","size":113457},{"uid":"50bdd80a3c1c23f0","name":"index_autocomplete","source":"50bdd80a3c1c23f0.png","type":"image/png","size":15267},{"uid":"f880c9d5442871a5","name":"index_console","source":"f880c9d5442871a5.json","type":"application/json","size":2,"content":[]}]},{"config":"Mobile Safari","suite":"searxng.spec.js","test_case":"search_general","attachments":[{"uid":"c5e854d1926964f1","name":"search_general","source":"c5e854d1926964f1.png","type":"image/png","size":691940},{"uid":"b3c62c5d3bb495ce","name":"search_general_2","source":"b3c62c5d3bb495ce.png","type":"image/png","size":219356},{"uid":"132774fcc9f15f87","name":"search_general_console","source":"132774fcc9f15f87.json","type":"application/json","size":2,"content":[]}]},{"config":"Mobile Safari","suite":"searxng.spec.js","test_case":"search_images","attachments":[{"uid":"ffbd8b0a082e5623","name":"search_images","source":"ffbd8b0a082e5623.png","type":"image/png","size":384944},{"uid":"38641b24e2bb2173","name":"search_images_detail","source":"38641b24e2bb2173.png","type":"image/png","size":553948},{"uid":"e84a84ec21d8b7ab","name":"search_images_console","source":"e84a84ec21d8b7ab.json","type":"application/json","size":2,"content":[]}]},{"config":"Mobile Safari","suite":"searxng.spec.js","test_case":"search_videos","attachments":[{"uid":"a43b79eccac56ec4","name":"search_videos","source":"a43b79eccac56ec4.png","type":"image/png","size":275767},{"uid":"f8223740f8c4c50","name":"search_videos_player","source":"f8223740f8c4c50.png","type":"image/png","size":275030},{"uid":"a0f3d7e4b238f620","name":"search_videos_console","source":"a0f3d7e4b238f620.json","type":"application/json","size":2,"content":[]}]},{"config":"Mobile Safari","suite":"searxng.spec.js","test_case":"search_map","attachments":[{"uid":"a22eff5a1595e06e","name":"search_map","source":"a22eff5a1595e06e.png","type":"image/png","size":427056},{"uid":"6750cc4e236a6670","name":"search_map_detail","source":"6750cc4e236a6670.png","type":"image/png","size":585128},{"uid":"badb3e5d27a9fe29","name":"search_map_console","source":"badb3e5d27a9fe29.json","type":"application/json","size":2,"content":[]}]},{"config":"Mobile Safari","suite":"searxng.spec.js","test_case":"search_code","attachments":[{"uid":"e7475621860c0542","name":"search_code","source":"e7475621860c0542.png","type":"image/png","size":118649},{"uid":"6a5f4fc8da6c6de0","name":"search_code_console","source":"6a5f4fc8da6c6de0.json","type":"application/json","size":2,"content":[]}]},{"config":"Mobile Safari","suite":"searxng.spec.js","test_case":"about","attachments":[{"uid":"49a781a8ba3c9e14","name":"about","source":"49a781a8ba3c9e14.png","type":"image/png","size":295897},{"uid":"803f013aa74b5c45","name":"about_console","source":"803f013aa74b5c45.json","type":"application/json","size":2,"content":[]}]}]